eckLEDurg/__init__.py
eckledurg-0.0.1.dist-info/METADATA
eckledurg-0.0.1.dist-info/WHEEL
eckledurg-0.0.1.dist-info/top_level.txt
eckledurg-0.0.1.dist-info/RECORD
