Metadata-Version: 2.4
Name: eckLEDurg
Version: 0.0.1
Summary: Computer Vision code for "seeing" LEDs with a camera automatically.
Author-email: Jakob Walker <Jakob.Walker@kratosdefense.com>
Project-URL: Homepage, https://code.devops.kratosdefense.com/projects/HWTST/repos/led-visual-detection/
Classifier: Programming Language :: Python :: 3
Requires-Python: >=3.7
Requires-Dist: opencv-python>=4.11.0
Requires-Dist: opencv-contrib-python>=4.11.0
